LICENSE
README.md
setup.py
parallel_statistics/__init__.py
parallel_statistics/hist.py
parallel_statistics/mean.py
parallel_statistics/mean_variance.py
parallel_statistics/sparse.py
parallel_statistics/sum.py
parallel_statistics/tools.py
parallel_statistics.egg-info/PKG-INFO
parallel_statistics.egg-info/SOURCES.txt
parallel_statistics.egg-info/dependency_links.txt
parallel_statistics.egg-info/requires.txt
parallel_statistics.egg-info/top_level.txt