Metadata-Version: 2.1
Name: parallel-statistics
Version: 0.13
Summary: Calculating basic statistics in parallel, incrementally
Home-page: https://github.com/LSSTDESC/parallel_statistics
Author: Joe Zuntz
Author-email: joe.zuntz@ed.ac.uk
License: UNKNOWN
Keywords: MPI,statistics
Platform: UNKNOWN
Classifier: Development Status :: 4 - Beta
Classifier: Intended Audience :: Developers
Classifier: License :: OSI Approved :: BSD License
Classifier: Programming Language :: Python :: 3
Classifier: Programming Language :: Python :: 3.6
Classifier: Programming Language :: Python :: 3.7
Classifier: Programming Language :: Python :: 3.8
Classifier: Programming Language :: Python :: 3 :: Only
Requires-Python: >=3.6
License-File: LICENSE
